dotpruner/__init__.py
dotpruner/__main__.py
dotpruner/dotpruner.py
dotpruner/utils.py
dotpruner-0.1.3.dist-info/LICENSE
dotpruner-0.1.3.dist-info/METADATA
dotpruner-0.1.3.dist-info/WHEEL
dotpruner-0.1.3.dist-info/top_level.txt
dotpruner-0.1.3.dist-info/RECORD
