Metadata-Version: 2.1
Name: dotpruner
Version: 0.1.3
Summary: Pruning redundant nodes from DOT graphs
Home-page: http://github.com/ansonmiu0214/dotpruner
Author: Anson Miu
Author-email: me@ansonmiu.dev
License: MIT
Platform: UNKNOWN
Classifier: Programming Language :: Python :: 3
Classifier: License :: OSI Approved :: MIT License
Classifier: Operating System :: OS Independent
Requires-Python: >=3.6
Requires-Dist: pydot
Requires-Dist: pyparsing
